datahub/__init__.py
datahub/__main__.py
datahub/entrypoints.py
datahub/py.typed
datahub/cli/__init__.py
datahub/cli/check_cli.py
datahub/cli/cli_utils.py
datahub/cli/delete_cli.py
datahub/cli/docker.py
datahub/cli/docker_check.py
datahub/cli/ingest_cli.py
datahub/cli/json_file.py
datahub/configuration/__init__.py
datahub/configuration/common.py
datahub/configuration/config_loader.py
datahub/configuration/import_resolver.py
datahub/configuration/kafka.py
datahub/configuration/toml.py
datahub/configuration/yaml.py
datahub/emitter/__init__.py
datahub/emitter/kafka_emitter.py
datahub/emitter/mce_builder.py
datahub/emitter/mcp.py
datahub/emitter/rest_emitter.py
datahub/emitter/serialization_helper.py
datahub/ingestion/__init__.py
datahub/ingestion/api/__init__.py
datahub/ingestion/api/closeable.py
datahub/ingestion/api/common.py
datahub/ingestion/api/registry.py
datahub/ingestion/api/report.py
datahub/ingestion/api/sink.py
datahub/ingestion/api/source.py
datahub/ingestion/api/transform.py
datahub/ingestion/api/workunit.py
datahub/ingestion/extractor/__init__.py
datahub/ingestion/extractor/extractor_registry.py
datahub/ingestion/extractor/mce_extractor.py
datahub/ingestion/extractor/schema_util.py
datahub/ingestion/run/__init__.py
datahub/ingestion/run/pipeline.py
datahub/ingestion/sink/__init__.py
datahub/ingestion/sink/console.py
datahub/ingestion/sink/datahub_kafka.py
datahub/ingestion/sink/datahub_rest.py
datahub/ingestion/sink/file.py
datahub/ingestion/sink/sink_registry.py
datahub/ingestion/source/__init__.py
datahub/ingestion/source/dbt.py
datahub/ingestion/source/feast.py
datahub/ingestion/source/file.py
datahub/ingestion/source/ge_data_profiler.py
datahub/ingestion/source/kafka.py
datahub/ingestion/source/kafka_connect.py
datahub/ingestion/source/ldap.py
datahub/ingestion/source/looker.py
datahub/ingestion/source/lookml.py
datahub/ingestion/source/metadata_common.py
datahub/ingestion/source/mongodb.py
datahub/ingestion/source/source_registry.py
thisbeatest-0.1.dist-info/METADATA
thisbeatest-0.1.dist-info/WHEEL
thisbeatest-0.1.dist-info/entry_points.txt
thisbeatest-0.1.dist-info/top_level.txt
thisbeatest-0.1.dist-info/RECORD
