Metadata-Version: 2.1
Name: thisbeatest
Version: 0.1
Summary: A CLI to work with DataHub metadata
Home-page: https://datahubproject.io/
License: Apache License 2.0
Project-URL: Documentation, https://datahubproject.io/docs/
Project-URL: Source, https://github.com/linkedin/datahub
Project-URL: Changelog, https://github.com/linkedin/datahub/releases
Platform: UNKNOWN
Classifier: Development Status :: 5 - Production/Stable
Classifier: Programming Language :: Python
Classifier: Programming Language :: Python :: 3
Classifier: Programming Language :: Python :: 3 :: Only
Classifier: Programming Language :: Python :: 3.6
Classifier: Programming Language :: Python :: 3.7
Classifier: Programming Language :: Python :: 3.8
Classifier: Programming Language :: Python :: 3.9
Classifier: Intended Audience :: Developers
Classifier: Intended Audience :: Information Technology
Classifier: Intended Audience :: System Administrators
Classifier: License :: OSI Approved
Classifier: License :: OSI Approved :: Apache Software License
Classifier: Operating System :: Unix
Classifier: Operating System :: POSIX :: Linux
Classifier: Environment :: Console
Classifier: Environment :: MacOS X
Classifier: Topic :: Software Development
Requires-Python: >=3.6
Requires-Dist: entrypoints
Requires-Dist: mypy-extensions (>=0.4.3)
Requires-Dist: python-dateutil
Requires-Dist: pydantic (>=1.5.1)
Requires-Dist: toml (>=0.10.0)
Requires-Dist: expandvars (>=0.6.5)
Requires-Dist: docker
Requires-Dist: click (>=6.0.0)
Requires-Dist: click-default-group
Requires-Dist: tabulate
Requires-Dist: avro-gen3 (==0.6.0)
Requires-Dist: typing-inspect
Requires-Dist: PyYAML
Requires-Dist: stackprinter
Requires-Dist: avro-python3 (>=1.8.2)
Requires-Dist: dataclasses (>=0.6) ; python_version < "3.7"
Requires-Dist: typing-extensions (>=3.7.4) ; python_version < "3.8"
Provides-Extra: airflow
Requires-Dist: entrypoints ; extra == 'airflow'
Requires-Dist: avro-gen3 (==0.6.0) ; extra == 'airflow'
Requires-Dist: apache-airflow (>=1.10.2) ; extra == 'airflow'
Requires-Dist: python-dateutil ; extra == 'airflow'
Requires-Dist: toml (>=0.10.0) ; extra == 'airflow'
Requires-Dist: PyYAML ; extra == 'airflow'
Requires-Dist: expandvars (>=0.6.5) ; extra == 'airflow'
Requires-Dist: stackprinter ; extra == 'airflow'
Requires-Dist: docker ; extra == 'airflow'
Requires-Dist: click (>=6.0.0) ; extra == 'airflow'
Requires-Dist: click-default-group ; extra == 'airflow'
Requires-Dist: tabulate ; extra == 'airflow'
Requires-Dist: avro-python3 (>=1.8.2) ; extra == 'airflow'
Provides-Extra: all
Requires-Dist: entrypoints ; extra == 'all'
Requires-Dist: cachetools ; extra == 'all'
Requires-Dist: sqlalchemy-pytds (>=0.3) ; extra == 'all'
Requires-Dist: apache-airflow (>=1.10.2) ; extra == 'all'
Requires-Dist: GeoAlchemy2 ; extra == 'all'
Requires-Dist: pymysql (>=1.0.2) ; extra == 'all'
Requires-Dist: fastavro (>=1.2.0) ; extra == 'all'
Requires-Dist: great-expectations ; extra == 'all'
Requires-Dist: acryl-pyhive[hive] (>=0.6.10) ; extra == 'all'
Requires-Dist: okta (~=1.7.0) ; extra == 'all'
Requires-Dist: sqlalchemy-redshift ; extra == 'all'
Requires-Dist: snowflake-sqlalchemy (<=1.2.4) ; extra == 'all'
Requires-Dist: cx-Oracle ; extra == 'all'
Requires-Dist: stackprinter ; extra == 'all'
Requires-Dist: pybigquery (>=0.6.0) ; extra == 'all'
Requires-Dist: requests ; extra == 'all'
Requires-Dist: sqlalchemy (==1.3.24) ; extra == 'all'
Requires-Dist: python-dateutil ; extra == 'all'
Requires-Dist: toml (>=0.10.0) ; extra == 'all'
Requires-Dist: pymongo (>=3.11) ; extra == 'all'
Requires-Dist: expandvars (>=0.6.5) ; extra == 'all'
Requires-Dist: docker ; extra == 'all'
Requires-Dist: click (>=6.0.0) ; extra == 'all'
Requires-Dist: click-default-group ; extra == 'all'
Requires-Dist: google-cloud-logging ; extra == 'all'
Requires-Dist: tabulate ; extra == 'all'
Requires-Dist: psycopg2-binary ; extra == 'all'
Requires-Dist: avro-gen3 (==0.6.0) ; extra == 'all'
Requires-Dist: looker-sdk (==21.6.0) ; extra == 'all'
Requires-Dist: lkml (>=1.1.0) ; extra == 'all'
Requires-Dist: PyYAML ; extra == 'all'
Requires-Dist: pydruid (>=0.6.2) ; extra == 'all'
Requires-Dist: sql-metadata (==2.2.1) ; extra == 'all'
Requires-Dist: boto3 ; extra == 'all'
Requires-Dist: PyAthena[sqlalchemy] ; extra == 'all'
Requires-Dist: python-ldap (>=2.4) ; extra == 'all'
Requires-Dist: confluent-kafka (>=1.5.0) ; extra == 'all'
Requires-Dist: avro-python3 (>=1.8.2) ; extra == 'all'
Provides-Extra: athena
Requires-Dist: entrypoints ; extra == 'athena'
Requires-Dist: avro-gen3 (==0.6.0) ; extra == 'athena'
Requires-Dist: sqlalchemy (==1.3.24) ; extra == 'athena'
Requires-Dist: python-dateutil ; extra == 'athena'
Requires-Dist: toml (>=0.10.0) ; extra == 'athena'
Requires-Dist: PyYAML ; extra == 'athena'
Requires-Dist: expandvars (>=0.6.5) ; extra == 'athena'
Requires-Dist: stackprinter ; extra == 'athena'
Requires-Dist: docker ; extra == 'athena'
Requires-Dist: click (>=6.0.0) ; extra == 'athena'
Requires-Dist: click-default-group ; extra == 'athena'
Requires-Dist: PyAthena[sqlalchemy] ; extra == 'athena'
Requires-Dist: tabulate ; extra == 'athena'
Requires-Dist: avro-python3 (>=1.8.2) ; extra == 'athena'
Provides-Extra: base
Requires-Dist: entrypoints ; extra == 'base'
Requires-Dist: avro-gen3 (==0.6.0) ; extra == 'base'
Requires-Dist: python-dateutil ; extra == 'base'
Requires-Dist: toml (>=0.10.0) ; extra == 'base'
Requires-Dist: PyYAML ; extra == 'base'
Requires-Dist: expandvars (>=0.6.5) ; extra == 'base'
Requires-Dist: stackprinter ; extra == 'base'
Requires-Dist: docker ; extra == 'base'
Requires-Dist: click (>=6.0.0) ; extra == 'base'
Requires-Dist: click-default-group ; extra == 'base'
Requires-Dist: tabulate ; extra == 'base'
Requires-Dist: avro-python3 (>=1.8.2) ; extra == 'base'
Provides-Extra: bigquery
Requires-Dist: pybigquery (>=0.6.0) ; extra == 'bigquery'
Requires-Dist: entrypoints ; extra == 'bigquery'
Requires-Dist: avro-gen3 (==0.6.0) ; extra == 'bigquery'
Requires-Dist: sqlalchemy (==1.3.24) ; extra == 'bigquery'
Requires-Dist: python-dateutil ; extra == 'bigquery'
Requires-Dist: toml (>=0.10.0) ; extra == 'bigquery'
Requires-Dist: PyYAML ; extra == 'bigquery'
Requires-Dist: expandvars (>=0.6.5) ; extra == 'bigquery'
Requires-Dist: stackprinter ; extra == 'bigquery'
Requires-Dist: docker ; extra == 'bigquery'
Requires-Dist: click (>=6.0.0) ; extra == 'bigquery'
Requires-Dist: click-default-group ; extra == 'bigquery'
Requires-Dist: tabulate ; extra == 'bigquery'
Requires-Dist: avro-python3 (>=1.8.2) ; extra == 'bigquery'
Provides-Extra: bigquery-usage
Requires-Dist: entrypoints ; extra == 'bigquery-usage'
Requires-Dist: avro-gen3 (==0.6.0) ; extra == 'bigquery-usage'
Requires-Dist: cachetools ; extra == 'bigquery-usage'
Requires-Dist: python-dateutil ; extra == 'bigquery-usage'
Requires-Dist: toml (>=0.10.0) ; extra == 'bigquery-usage'
Requires-Dist: PyYAML ; extra == 'bigquery-usage'
Requires-Dist: expandvars (>=0.6.5) ; extra == 'bigquery-usage'
Requires-Dist: stackprinter ; extra == 'bigquery-usage'
Requires-Dist: docker ; extra == 'bigquery-usage'
Requires-Dist: click (>=6.0.0) ; extra == 'bigquery-usage'
Requires-Dist: click-default-group ; extra == 'bigquery-usage'
Requires-Dist: google-cloud-logging ; extra == 'bigquery-usage'
Requires-Dist: tabulate ; extra == 'bigquery-usage'
Requires-Dist: avro-python3 (>=1.8.2) ; extra == 'bigquery-usage'
Provides-Extra: datahub-kafka
Requires-Dist: entrypoints ; extra == 'datahub-kafka'
Requires-Dist: avro-gen3 (==0.6.0) ; extra == 'datahub-kafka'
Requires-Dist: python-dateutil ; extra == 'datahub-kafka'
Requires-Dist: toml (>=0.10.0) ; extra == 'datahub-kafka'
Requires-Dist: PyYAML ; extra == 'datahub-kafka'
Requires-Dist: expandvars (>=0.6.5) ; extra == 'datahub-kafka'
Requires-Dist: stackprinter ; extra == 'datahub-kafka'
Requires-Dist: docker ; extra == 'datahub-kafka'
Requires-Dist: fastavro (>=1.2.0) ; extra == 'datahub-kafka'
Requires-Dist: click (>=6.0.0) ; extra == 'datahub-kafka'
Requires-Dist: click-default-group ; extra == 'datahub-kafka'
Requires-Dist: confluent-kafka (>=1.5.0) ; extra == 'datahub-kafka'
Requires-Dist: tabulate ; extra == 'datahub-kafka'
Requires-Dist: avro-python3 (>=1.8.2) ; extra == 'datahub-kafka'
Provides-Extra: datahub-rest
Requires-Dist: entrypoints ; extra == 'datahub-rest'
Requires-Dist: avro-gen3 (==0.6.0) ; extra == 'datahub-rest'
Requires-Dist: requests ; extra == 'datahub-rest'
Requires-Dist: python-dateutil ; extra == 'datahub-rest'
Requires-Dist: toml (>=0.10.0) ; extra == 'datahub-rest'
Requires-Dist: PyYAML ; extra == 'datahub-rest'
Requires-Dist: expandvars (>=0.6.5) ; extra == 'datahub-rest'
Requires-Dist: stackprinter ; extra == 'datahub-rest'
Requires-Dist: docker ; extra == 'datahub-rest'
Requires-Dist: click (>=6.0.0) ; extra == 'datahub-rest'
Requires-Dist: click-default-group ; extra == 'datahub-rest'
Requires-Dist: tabulate ; extra == 'datahub-rest'
Requires-Dist: avro-python3 (>=1.8.2) ; extra == 'datahub-rest'
Provides-Extra: dbt
Requires-Dist: entrypoints ; extra == 'dbt'
Requires-Dist: avro-gen3 (==0.6.0) ; extra == 'dbt'
Requires-Dist: python-dateutil ; extra == 'dbt'
Requires-Dist: toml (>=0.10.0) ; extra == 'dbt'
Requires-Dist: PyYAML ; extra == 'dbt'
Requires-Dist: expandvars (>=0.6.5) ; extra == 'dbt'
Requires-Dist: stackprinter ; extra == 'dbt'
Requires-Dist: docker ; extra == 'dbt'
Requires-Dist: click (>=6.0.0) ; extra == 'dbt'
Requires-Dist: click-default-group ; extra == 'dbt'
Requires-Dist: tabulate ; extra == 'dbt'
Requires-Dist: avro-python3 (>=1.8.2) ; extra == 'dbt'
Provides-Extra: dev
Requires-Dist: entrypoints ; extra == 'dev'
Requires-Dist: pytest-cov (>=2.8.1) ; extra == 'dev'
Requires-Dist: types-freezegun ; extra == 'dev'
Requires-Dist: cachetools ; extra == 'dev'
Requires-Dist: types-PyMySQL ; extra == 'dev'
Requires-Dist: types-tabulate ; extra == 'dev'
Requires-Dist: GeoAlchemy2 ; extra == 'dev'
Requires-Dist: fastavro (>=1.2.0) ; extra == 'dev'
Requires-Dist: isort (>=5.7.0) ; extra == 'dev'
Requires-Dist: coverage (>=5.1) ; extra == 'dev'
Requires-Dist: typing-inspect ; extra == 'dev'
Requires-Dist: pytest-docker (>=0.10.3) ; extra == 'dev'
Requires-Dist: types-PyYAML ; extra == 'dev'
Requires-Dist: pytest (>=6.2.2) ; extra == 'dev'
Requires-Dist: jsonpickle ; extra == 'dev'
Requires-Dist: requests-mock ; extra == 'dev'
Requires-Dist: flake8-tidy-imports (>=4.3.0) ; extra == 'dev'
Requires-Dist: okta (~=1.7.0) ; extra == 'dev'
Requires-Dist: snowflake-sqlalchemy (<=1.2.4) ; extra == 'dev'
Requires-Dist: black (>=19.10b0) ; extra == 'dev'
Requires-Dist: twine ; extra == 'dev'
Requires-Dist: mypy (>=0.901) ; extra == 'dev'
Requires-Dist: cx-Oracle ; extra == 'dev'
Requires-Dist: stackprinter ; extra == 'dev'
Requires-Dist: types-dataclasses ; extra == 'dev'
Requires-Dist: deepdiff ; extra == 'dev'
Requires-Dist: freezegun ; extra == 'dev'
Requires-Dist: types-toml ; extra == 'dev'
Requires-Dist: types-cachetools ; extra == 'dev'
Requires-Dist: flake8 (>=3.8.3) ; extra == 'dev'
Requires-Dist: pybigquery (>=0.6.0) ; extra == 'dev'
Requires-Dist: mypy-extensions (>=0.4.3) ; extra == 'dev'
Requires-Dist: types-click (==0.1.12) ; extra == 'dev'
Requires-Dist: sqlalchemy (==1.3.24) ; extra == 'dev'
Requires-Dist: python-dateutil ; extra == 'dev'
Requires-Dist: pydantic (>=1.5.1) ; extra == 'dev'
Requires-Dist: toml (>=0.10.0) ; extra == 'dev'
Requires-Dist: types-pkg-resources ; extra == 'dev'
Requires-Dist: requests ; extra == 'dev'
Requires-Dist: apache-airflow[snowflake] (>=2.0.2) ; extra == 'dev'
Requires-Dist: expandvars (>=0.6.5) ; extra == 'dev'
Requires-Dist: docker ; extra == 'dev'
Requires-Dist: click (>=6.0.0) ; extra == 'dev'
Requires-Dist: click-default-group ; extra == 'dev'
Requires-Dist: boto3-stubs[glue,s3,sagemaker] ; extra == 'dev'
Requires-Dist: google-cloud-logging ; extra == 'dev'
Requires-Dist: tabulate ; extra == 'dev'
Requires-Dist: types-six ; extra == 'dev'
Requires-Dist: tox ; extra == 'dev'
Requires-Dist: avro-gen3 (==0.6.0) ; extra == 'dev'
Requires-Dist: psycopg2-binary ; extra == 'dev'
Requires-Dist: looker-sdk (==21.6.0) ; extra == 'dev'
Requires-Dist: lkml (>=1.1.0) ; extra == 'dev'
Requires-Dist: PyYAML ; extra == 'dev'
Requires-Dist: sqlalchemy-stubs ; extra == 'dev'
Requires-Dist: build ; extra == 'dev'
Requires-Dist: types-python-dateutil ; extra == 'dev'
Requires-Dist: types-requests ; extra == 'dev'
Requires-Dist: sql-metadata (==2.2.1) ; extra == 'dev'
Requires-Dist: boto3 ; extra == 'dev'
Requires-Dist: confluent-kafka (>=1.5.0) ; extra == 'dev'
Requires-Dist: avro-python3 (>=1.8.2) ; extra == 'dev'
Provides-Extra: dev-airflow1
Requires-Dist: entrypoints ; extra == 'dev-airflow1'
Requires-Dist: pytest-cov (>=2.8.1) ; extra == 'dev-airflow1'
Requires-Dist: types-freezegun ; extra == 'dev-airflow1'
Requires-Dist: cachetools ; extra == 'dev-airflow1'
Requires-Dist: apache-airflow (==1.10.15) ; extra == 'dev-airflow1'
Requires-Dist: types-PyMySQL ; extra == 'dev-airflow1'
Requires-Dist: types-tabulate ; extra == 'dev-airflow1'
Requires-Dist: GeoAlchemy2 ; extra == 'dev-airflow1'
Requires-Dist: fastavro (>=1.2.0) ; extra == 'dev-airflow1'
Requires-Dist: isort (>=5.7.0) ; extra == 'dev-airflow1'
Requires-Dist: coverage (>=5.1) ; extra == 'dev-airflow1'
Requires-Dist: typing-inspect ; extra == 'dev-airflow1'
Requires-Dist: pytest-docker (>=0.10.3) ; extra == 'dev-airflow1'
Requires-Dist: types-PyYAML ; extra == 'dev-airflow1'
Requires-Dist: pytest (>=6.2.2) ; extra == 'dev-airflow1'
Requires-Dist: jsonpickle ; extra == 'dev-airflow1'
Requires-Dist: requests-mock ; extra == 'dev-airflow1'
Requires-Dist: flake8-tidy-imports (>=4.3.0) ; extra == 'dev-airflow1'
Requires-Dist: okta (~=1.7.0) ; extra == 'dev-airflow1'
Requires-Dist: snowflake-sqlalchemy (<=1.2.4) ; extra == 'dev-airflow1'
Requires-Dist: apache-airflow-backport-providers-snowflake ; extra == 'dev-airflow1'
Requires-Dist: black (>=19.10b0) ; extra == 'dev-airflow1'
Requires-Dist: twine ; extra == 'dev-airflow1'
Requires-Dist: mypy (>=0.901) ; extra == 'dev-airflow1'
Requires-Dist: cx-Oracle ; extra == 'dev-airflow1'
Requires-Dist: stackprinter ; extra == 'dev-airflow1'
Requires-Dist: types-dataclasses ; extra == 'dev-airflow1'
Requires-Dist: deepdiff ; extra == 'dev-airflow1'
Requires-Dist: freezegun ; extra == 'dev-airflow1'
Requires-Dist: types-toml ; extra == 'dev-airflow1'
Requires-Dist: types-cachetools ; extra == 'dev-airflow1'
Requires-Dist: flake8 (>=3.8.3) ; extra == 'dev-airflow1'
Requires-Dist: pybigquery (>=0.6.0) ; extra == 'dev-airflow1'
Requires-Dist: mypy-extensions (>=0.4.3) ; extra == 'dev-airflow1'
Requires-Dist: types-click (==0.1.12) ; extra == 'dev-airflow1'
Requires-Dist: sqlalchemy (==1.3.24) ; extra == 'dev-airflow1'
Requires-Dist: python-dateutil ; extra == 'dev-airflow1'
Requires-Dist: pydantic (>=1.5.1) ; extra == 'dev-airflow1'
Requires-Dist: toml (>=0.10.0) ; extra == 'dev-airflow1'
Requires-Dist: types-pkg-resources ; extra == 'dev-airflow1'
Requires-Dist: requests ; extra == 'dev-airflow1'
Requires-Dist: expandvars (>=0.6.5) ; extra == 'dev-airflow1'
Requires-Dist: docker ; extra == 'dev-airflow1'
Requires-Dist: click (>=6.0.0) ; extra == 'dev-airflow1'
Requires-Dist: click-default-group ; extra == 'dev-airflow1'
Requires-Dist: boto3-stubs[glue,s3,sagemaker] ; extra == 'dev-airflow1'
Requires-Dist: google-cloud-logging ; extra == 'dev-airflow1'
Requires-Dist: tabulate ; extra == 'dev-airflow1'
Requires-Dist: types-six ; extra == 'dev-airflow1'
Requires-Dist: tox ; extra == 'dev-airflow1'
Requires-Dist: avro-gen3 (==0.6.0) ; extra == 'dev-airflow1'
Requires-Dist: psycopg2-binary ; extra == 'dev-airflow1'
Requires-Dist: looker-sdk (==21.6.0) ; extra == 'dev-airflow1'
Requires-Dist: lkml (>=1.1.0) ; extra == 'dev-airflow1'
Requires-Dist: PyYAML ; extra == 'dev-airflow1'
Requires-Dist: sqlalchemy-stubs ; extra == 'dev-airflow1'
Requires-Dist: build ; extra == 'dev-airflow1'
Requires-Dist: types-python-dateutil ; extra == 'dev-airflow1'
Requires-Dist: types-requests ; extra == 'dev-airflow1'
Requires-Dist: sql-metadata (==2.2.1) ; extra == 'dev-airflow1'
Requires-Dist: boto3 ; extra == 'dev-airflow1'
Requires-Dist: confluent-kafka (>=1.5.0) ; extra == 'dev-airflow1'
Requires-Dist: avro-python3 (>=1.8.2) ; extra == 'dev-airflow1'
Requires-Dist: dataclasses (>=0.6) ; (python_version < "3.7") and extra == 'dev-airflow1'
Requires-Dist: typing-extensions (>=3.7.4) ; (python_version < "3.8") and extra == 'dev-airflow1'
Requires-Dist: dataclasses (>=0.6) ; (python_version < "3.7") and extra == 'dev'
Requires-Dist: typing-extensions (>=3.7.4) ; (python_version < "3.8") and extra == 'dev'
Provides-Extra: druid
Requires-Dist: entrypoints ; extra == 'druid'
Requires-Dist: avro-gen3 (==0.6.0) ; extra == 'druid'
Requires-Dist: sqlalchemy (==1.3.24) ; extra == 'druid'
Requires-Dist: python-dateutil ; extra == 'druid'
Requires-Dist: toml (>=0.10.0) ; extra == 'druid'
Requires-Dist: PyYAML ; extra == 'druid'
Requires-Dist: pydruid (>=0.6.2) ; extra == 'druid'
Requires-Dist: expandvars (>=0.6.5) ; extra == 'druid'
Requires-Dist: stackprinter ; extra == 'druid'
Requires-Dist: docker ; extra == 'druid'
Requires-Dist: click (>=6.0.0) ; extra == 'druid'
Requires-Dist: click-default-group ; extra == 'druid'
Requires-Dist: tabulate ; extra == 'druid'
Requires-Dist: avro-python3 (>=1.8.2) ; extra == 'druid'
Provides-Extra: feast
Requires-Dist: entrypoints ; extra == 'feast'
Requires-Dist: avro-gen3 (==0.6.0) ; extra == 'feast'
Requires-Dist: python-dateutil ; extra == 'feast'
Requires-Dist: toml (>=0.10.0) ; extra == 'feast'
Requires-Dist: PyYAML ; extra == 'feast'
Requires-Dist: expandvars (>=0.6.5) ; extra == 'feast'
Requires-Dist: stackprinter ; extra == 'feast'
Requires-Dist: docker ; extra == 'feast'
Requires-Dist: click (>=6.0.0) ; extra == 'feast'
Requires-Dist: click-default-group ; extra == 'feast'
Requires-Dist: tabulate ; extra == 'feast'
Requires-Dist: avro-python3 (>=1.8.2) ; extra == 'feast'
Provides-Extra: glue
Requires-Dist: entrypoints ; extra == 'glue'
Requires-Dist: avro-gen3 (==0.6.0) ; extra == 'glue'
Requires-Dist: python-dateutil ; extra == 'glue'
Requires-Dist: toml (>=0.10.0) ; extra == 'glue'
Requires-Dist: PyYAML ; extra == 'glue'
Requires-Dist: expandvars (>=0.6.5) ; extra == 'glue'
Requires-Dist: stackprinter ; extra == 'glue'
Requires-Dist: docker ; extra == 'glue'
Requires-Dist: click (>=6.0.0) ; extra == 'glue'
Requires-Dist: boto3 ; extra == 'glue'
Requires-Dist: click-default-group ; extra == 'glue'
Requires-Dist: tabulate ; extra == 'glue'
Requires-Dist: avro-python3 (>=1.8.2) ; extra == 'glue'
Provides-Extra: hive
Requires-Dist: entrypoints ; extra == 'hive'
Requires-Dist: avro-gen3 (==0.6.0) ; extra == 'hive'
Requires-Dist: acryl-pyhive[hive] (>=0.6.10) ; extra == 'hive'
Requires-Dist: sqlalchemy (==1.3.24) ; extra == 'hive'
Requires-Dist: python-dateutil ; extra == 'hive'
Requires-Dist: toml (>=0.10.0) ; extra == 'hive'
Requires-Dist: PyYAML ; extra == 'hive'
Requires-Dist: expandvars (>=0.6.5) ; extra == 'hive'
Requires-Dist: stackprinter ; extra == 'hive'
Requires-Dist: docker ; extra == 'hive'
Requires-Dist: click (>=6.0.0) ; extra == 'hive'
Requires-Dist: click-default-group ; extra == 'hive'
Requires-Dist: tabulate ; extra == 'hive'
Requires-Dist: avro-python3 (>=1.8.2) ; extra == 'hive'
Provides-Extra: integration-tests
Requires-Dist: acryl-pyhive[hive] (>=0.6.10) ; extra == 'integration-tests'
Requires-Dist: sqlalchemy-pytds (>=0.3) ; extra == 'integration-tests'
Requires-Dist: sqlalchemy (==1.3.24) ; extra == 'integration-tests'
Requires-Dist: snowflake-sqlalchemy (<=1.2.4) ; extra == 'integration-tests'
Requires-Dist: pymongo (>=3.11) ; extra == 'integration-tests'
Requires-Dist: pydruid (>=0.6.2) ; extra == 'integration-tests'
Requires-Dist: pymysql (>=1.0.2) ; extra == 'integration-tests'
Requires-Dist: docker ; extra == 'integration-tests'
Requires-Dist: python-ldap (>=2.4) ; extra == 'integration-tests'
Requires-Dist: great-expectations ; extra == 'integration-tests'
Provides-Extra: kafka
Requires-Dist: entrypoints ; extra == 'kafka'
Requires-Dist: avro-gen3 (==0.6.0) ; extra == 'kafka'
Requires-Dist: python-dateutil ; extra == 'kafka'
Requires-Dist: toml (>=0.10.0) ; extra == 'kafka'
Requires-Dist: PyYAML ; extra == 'kafka'
Requires-Dist: expandvars (>=0.6.5) ; extra == 'kafka'
Requires-Dist: stackprinter ; extra == 'kafka'
Requires-Dist: docker ; extra == 'kafka'
Requires-Dist: fastavro (>=1.2.0) ; extra == 'kafka'
Requires-Dist: click (>=6.0.0) ; extra == 'kafka'
Requires-Dist: click-default-group ; extra == 'kafka'
Requires-Dist: confluent-kafka (>=1.5.0) ; extra == 'kafka'
Requires-Dist: tabulate ; extra == 'kafka'
Requires-Dist: avro-python3 (>=1.8.2) ; extra == 'kafka'
Provides-Extra: kafka-connect
Requires-Dist: entrypoints ; extra == 'kafka-connect'
Requires-Dist: avro-gen3 (==0.6.0) ; extra == 'kafka-connect'
Requires-Dist: requests ; extra == 'kafka-connect'
Requires-Dist: sqlalchemy (==1.3.24) ; extra == 'kafka-connect'
Requires-Dist: python-dateutil ; extra == 'kafka-connect'
Requires-Dist: toml (>=0.10.0) ; extra == 'kafka-connect'
Requires-Dist: PyYAML ; extra == 'kafka-connect'
Requires-Dist: expandvars (>=0.6.5) ; extra == 'kafka-connect'
Requires-Dist: stackprinter ; extra == 'kafka-connect'
Requires-Dist: docker ; extra == 'kafka-connect'
Requires-Dist: click (>=6.0.0) ; extra == 'kafka-connect'
Requires-Dist: click-default-group ; extra == 'kafka-connect'
Requires-Dist: tabulate ; extra == 'kafka-connect'
Requires-Dist: avro-python3 (>=1.8.2) ; extra == 'kafka-connect'
Provides-Extra: ldap
Requires-Dist: entrypoints ; extra == 'ldap'
Requires-Dist: avro-gen3 (==0.6.0) ; extra == 'ldap'
Requires-Dist: python-dateutil ; extra == 'ldap'
Requires-Dist: toml (>=0.10.0) ; extra == 'ldap'
Requires-Dist: PyYAML ; extra == 'ldap'
Requires-Dist: expandvars (>=0.6.5) ; extra == 'ldap'
Requires-Dist: stackprinter ; extra == 'ldap'
Requires-Dist: docker ; extra == 'ldap'
Requires-Dist: click (>=6.0.0) ; extra == 'ldap'
Requires-Dist: click-default-group ; extra == 'ldap'
Requires-Dist: python-ldap (>=2.4) ; extra == 'ldap'
Requires-Dist: tabulate ; extra == 'ldap'
Requires-Dist: avro-python3 (>=1.8.2) ; extra == 'ldap'
Provides-Extra: looker
Requires-Dist: entrypoints ; extra == 'looker'
Requires-Dist: avro-gen3 (==0.6.0) ; extra == 'looker'
Requires-Dist: looker-sdk (==21.6.0) ; extra == 'looker'
Requires-Dist: python-dateutil ; extra == 'looker'
Requires-Dist: toml (>=0.10.0) ; extra == 'looker'
Requires-Dist: PyYAML ; extra == 'looker'
Requires-Dist: expandvars (>=0.6.5) ; extra == 'looker'
Requires-Dist: stackprinter ; extra == 'looker'
Requires-Dist: docker ; extra == 'looker'
Requires-Dist: click (>=6.0.0) ; extra == 'looker'
Requires-Dist: click-default-group ; extra == 'looker'
Requires-Dist: tabulate ; extra == 'looker'
Requires-Dist: avro-python3 (>=1.8.2) ; extra == 'looker'
Provides-Extra: lookml
Requires-Dist: entrypoints ; extra == 'lookml'
Requires-Dist: avro-gen3 (==0.6.0) ; extra == 'lookml'
Requires-Dist: python-dateutil ; extra == 'lookml'
Requires-Dist: toml (>=0.10.0) ; extra == 'lookml'
Requires-Dist: lkml (>=1.1.0) ; extra == 'lookml'
Requires-Dist: PyYAML ; extra == 'lookml'
Requires-Dist: expandvars (>=0.6.5) ; extra == 'lookml'
Requires-Dist: stackprinter ; extra == 'lookml'
Requires-Dist: docker ; extra == 'lookml'
Requires-Dist: click (>=6.0.0) ; extra == 'lookml'
Requires-Dist: sql-metadata (==2.2.1) ; extra == 'lookml'
Requires-Dist: click-default-group ; extra == 'lookml'
Requires-Dist: tabulate ; extra == 'lookml'
Requires-Dist: avro-python3 (>=1.8.2) ; extra == 'lookml'
Provides-Extra: mongodb
Requires-Dist: entrypoints ; extra == 'mongodb'
Requires-Dist: avro-gen3 (==0.6.0) ; extra == 'mongodb'
Requires-Dist: python-dateutil ; extra == 'mongodb'
Requires-Dist: toml (>=0.10.0) ; extra == 'mongodb'
Requires-Dist: PyYAML ; extra == 'mongodb'
Requires-Dist: pymongo (>=3.11) ; extra == 'mongodb'
Requires-Dist: expandvars (>=0.6.5) ; extra == 'mongodb'
Requires-Dist: stackprinter ; extra == 'mongodb'
Requires-Dist: docker ; extra == 'mongodb'
Requires-Dist: click (>=6.0.0) ; extra == 'mongodb'
Requires-Dist: click-default-group ; extra == 'mongodb'
Requires-Dist: tabulate ; extra == 'mongodb'
Requires-Dist: avro-python3 (>=1.8.2) ; extra == 'mongodb'
Provides-Extra: mssql
Requires-Dist: entrypoints ; extra == 'mssql'
Requires-Dist: avro-gen3 (==0.6.0) ; extra == 'mssql'
Requires-Dist: sqlalchemy-pytds (>=0.3) ; extra == 'mssql'
Requires-Dist: sqlalchemy (==1.3.24) ; extra == 'mssql'
Requires-Dist: python-dateutil ; extra == 'mssql'
Requires-Dist: toml (>=0.10.0) ; extra == 'mssql'
Requires-Dist: PyYAML ; extra == 'mssql'
Requires-Dist: expandvars (>=0.6.5) ; extra == 'mssql'
Requires-Dist: stackprinter ; extra == 'mssql'
Requires-Dist: docker ; extra == 'mssql'
Requires-Dist: click (>=6.0.0) ; extra == 'mssql'
Requires-Dist: click-default-group ; extra == 'mssql'
Requires-Dist: tabulate ; extra == 'mssql'
Requires-Dist: avro-python3 (>=1.8.2) ; extra == 'mssql'
Provides-Extra: mssql-odbc
Requires-Dist: pyodbc ; extra == 'mssql-odbc'
Requires-Dist: entrypoints ; extra == 'mssql-odbc'
Requires-Dist: avro-gen3 (==0.6.0) ; extra == 'mssql-odbc'
Requires-Dist: sqlalchemy (==1.3.24) ; extra == 'mssql-odbc'
Requires-Dist: python-dateutil ; extra == 'mssql-odbc'
Requires-Dist: toml (>=0.10.0) ; extra == 'mssql-odbc'
Requires-Dist: PyYAML ; extra == 'mssql-odbc'
Requires-Dist: expandvars (>=0.6.5) ; extra == 'mssql-odbc'
Requires-Dist: stackprinter ; extra == 'mssql-odbc'
Requires-Dist: docker ; extra == 'mssql-odbc'
Requires-Dist: click (>=6.0.0) ; extra == 'mssql-odbc'
Requires-Dist: click-default-group ; extra == 'mssql-odbc'
Requires-Dist: tabulate ; extra == 'mssql-odbc'
Requires-Dist: avro-python3 (>=1.8.2) ; extra == 'mssql-odbc'
Provides-Extra: mysql
Requires-Dist: entrypoints ; extra == 'mysql'
Requires-Dist: avro-gen3 (==0.6.0) ; extra == 'mysql'
Requires-Dist: sqlalchemy (==1.3.24) ; extra == 'mysql'
Requires-Dist: python-dateutil ; extra == 'mysql'
Requires-Dist: toml (>=0.10.0) ; extra == 'mysql'
Requires-Dist: PyYAML ; extra == 'mysql'
Requires-Dist: expandvars (>=0.6.5) ; extra == 'mysql'
Requires-Dist: stackprinter ; extra == 'mysql'
Requires-Dist: docker ; extra == 'mysql'
Requires-Dist: pymysql (>=1.0.2) ; extra == 'mysql'
Requires-Dist: click (>=6.0.0) ; extra == 'mysql'
Requires-Dist: click-default-group ; extra == 'mysql'
Requires-Dist: tabulate ; extra == 'mysql'
Requires-Dist: avro-python3 (>=1.8.2) ; extra == 'mysql'
Provides-Extra: okta
Requires-Dist: entrypoints ; extra == 'okta'
Requires-Dist: avro-gen3 (==0.6.0) ; extra == 'okta'
Requires-Dist: okta (~=1.7.0) ; extra == 'okta'
Requires-Dist: python-dateutil ; extra == 'okta'
Requires-Dist: toml (>=0.10.0) ; extra == 'okta'
Requires-Dist: PyYAML ; extra == 'okta'
Requires-Dist: expandvars (>=0.6.5) ; extra == 'okta'
Requires-Dist: stackprinter ; extra == 'okta'
Requires-Dist: docker ; extra == 'okta'
Requires-Dist: click (>=6.0.0) ; extra == 'okta'
Requires-Dist: click-default-group ; extra == 'okta'
Requires-Dist: tabulate ; extra == 'okta'
Requires-Dist: avro-python3 (>=1.8.2) ; extra == 'okta'
Provides-Extra: oracle
Requires-Dist: entrypoints ; extra == 'oracle'
Requires-Dist: avro-gen3 (==0.6.0) ; extra == 'oracle'
Requires-Dist: sqlalchemy (==1.3.24) ; extra == 'oracle'
Requires-Dist: python-dateutil ; extra == 'oracle'
Requires-Dist: toml (>=0.10.0) ; extra == 'oracle'
Requires-Dist: PyYAML ; extra == 'oracle'
Requires-Dist: cx-Oracle ; extra == 'oracle'
Requires-Dist: expandvars (>=0.6.5) ; extra == 'oracle'
Requires-Dist: stackprinter ; extra == 'oracle'
Requires-Dist: docker ; extra == 'oracle'
Requires-Dist: click (>=6.0.0) ; extra == 'oracle'
Requires-Dist: click-default-group ; extra == 'oracle'
Requires-Dist: tabulate ; extra == 'oracle'
Requires-Dist: avro-python3 (>=1.8.2) ; extra == 'oracle'
Provides-Extra: postgres
Requires-Dist: psycopg2-binary ; extra == 'postgres'
Requires-Dist: entrypoints ; extra == 'postgres'
Requires-Dist: avro-gen3 (==0.6.0) ; extra == 'postgres'
Requires-Dist: sqlalchemy (==1.3.24) ; extra == 'postgres'
Requires-Dist: python-dateutil ; extra == 'postgres'
Requires-Dist: toml (>=0.10.0) ; extra == 'postgres'
Requires-Dist: PyYAML ; extra == 'postgres'
Requires-Dist: expandvars (>=0.6.5) ; extra == 'postgres'
Requires-Dist: stackprinter ; extra == 'postgres'
Requires-Dist: docker ; extra == 'postgres'
Requires-Dist: GeoAlchemy2 ; extra == 'postgres'
Requires-Dist: click (>=6.0.0) ; extra == 'postgres'
Requires-Dist: click-default-group ; extra == 'postgres'
Requires-Dist: tabulate ; extra == 'postgres'
Requires-Dist: avro-python3 (>=1.8.2) ; extra == 'postgres'
Provides-Extra: redshift
Requires-Dist: psycopg2-binary ; extra == 'redshift'
Requires-Dist: entrypoints ; extra == 'redshift'
Requires-Dist: avro-gen3 (==0.6.0) ; extra == 'redshift'
Requires-Dist: sqlalchemy (==1.3.24) ; extra == 'redshift'
Requires-Dist: python-dateutil ; extra == 'redshift'
Requires-Dist: toml (>=0.10.0) ; extra == 'redshift'
Requires-Dist: sqlalchemy-redshift ; extra == 'redshift'
Requires-Dist: PyYAML ; extra == 'redshift'
Requires-Dist: expandvars (>=0.6.5) ; extra == 'redshift'
Requires-Dist: stackprinter ; extra == 'redshift'
Requires-Dist: docker ; extra == 'redshift'
Requires-Dist: GeoAlchemy2 ; extra == 'redshift'
Requires-Dist: click (>=6.0.0) ; extra == 'redshift'
Requires-Dist: click-default-group ; extra == 'redshift'
Requires-Dist: tabulate ; extra == 'redshift'
Requires-Dist: avro-python3 (>=1.8.2) ; extra == 'redshift'
Provides-Extra: sagemaker
Requires-Dist: entrypoints ; extra == 'sagemaker'
Requires-Dist: avro-gen3 (==0.6.0) ; extra == 'sagemaker'
Requires-Dist: python-dateutil ; extra == 'sagemaker'
Requires-Dist: toml (>=0.10.0) ; extra == 'sagemaker'
Requires-Dist: PyYAML ; extra == 'sagemaker'
Requires-Dist: expandvars (>=0.6.5) ; extra == 'sagemaker'
Requires-Dist: stackprinter ; extra == 'sagemaker'
Requires-Dist: docker ; extra == 'sagemaker'
Requires-Dist: click (>=6.0.0) ; extra == 'sagemaker'
Requires-Dist: boto3 ; extra == 'sagemaker'
Requires-Dist: click-default-group ; extra == 'sagemaker'
Requires-Dist: tabulate ; extra == 'sagemaker'
Requires-Dist: avro-python3 (>=1.8.2) ; extra == 'sagemaker'
Provides-Extra: snowflake
Requires-Dist: entrypoints ; extra == 'snowflake'
Requires-Dist: avro-gen3 (==0.6.0) ; extra == 'snowflake'
Requires-Dist: snowflake-sqlalchemy (<=1.2.4) ; extra == 'snowflake'
Requires-Dist: python-dateutil ; extra == 'snowflake'
Requires-Dist: toml (>=0.10.0) ; extra == 'snowflake'
Requires-Dist: sqlalchemy (==1.3.24) ; extra == 'snowflake'
Requires-Dist: PyYAML ; extra == 'snowflake'
Requires-Dist: expandvars (>=0.6.5) ; extra == 'snowflake'
Requires-Dist: stackprinter ; extra == 'snowflake'
Requires-Dist: docker ; extra == 'snowflake'
Requires-Dist: click (>=6.0.0) ; extra == 'snowflake'
Requires-Dist: click-default-group ; extra == 'snowflake'
Requires-Dist: tabulate ; extra == 'snowflake'
Requires-Dist: avro-python3 (>=1.8.2) ; extra == 'snowflake'
Provides-Extra: snowflake-usage
Requires-Dist: entrypoints ; extra == 'snowflake-usage'
Requires-Dist: avro-gen3 (==0.6.0) ; extra == 'snowflake-usage'
Requires-Dist: snowflake-sqlalchemy (<=1.2.4) ; extra == 'snowflake-usage'
Requires-Dist: python-dateutil ; extra == 'snowflake-usage'
Requires-Dist: toml (>=0.10.0) ; extra == 'snowflake-usage'
Requires-Dist: sqlalchemy (==1.3.24) ; extra == 'snowflake-usage'
Requires-Dist: PyYAML ; extra == 'snowflake-usage'
Requires-Dist: expandvars (>=0.6.5) ; extra == 'snowflake-usage'
Requires-Dist: stackprinter ; extra == 'snowflake-usage'
Requires-Dist: docker ; extra == 'snowflake-usage'
Requires-Dist: click (>=6.0.0) ; extra == 'snowflake-usage'
Requires-Dist: click-default-group ; extra == 'snowflake-usage'
Requires-Dist: tabulate ; extra == 'snowflake-usage'
Requires-Dist: avro-python3 (>=1.8.2) ; extra == 'snowflake-usage'
Provides-Extra: sql-profiles
Requires-Dist: entrypoints ; extra == 'sql-profiles'
Requires-Dist: avro-gen3 (==0.6.0) ; extra == 'sql-profiles'
Requires-Dist: sqlalchemy (==1.3.24) ; extra == 'sql-profiles'
Requires-Dist: python-dateutil ; extra == 'sql-profiles'
Requires-Dist: toml (>=0.10.0) ; extra == 'sql-profiles'
Requires-Dist: PyYAML ; extra == 'sql-profiles'
Requires-Dist: expandvars (>=0.6.5) ; extra == 'sql-profiles'
Requires-Dist: stackprinter ; extra == 'sql-profiles'
Requires-Dist: docker ; extra == 'sql-profiles'
Requires-Dist: click (>=6.0.0) ; extra == 'sql-profiles'
Requires-Dist: click-default-group ; extra == 'sql-profiles'
Requires-Dist: great-expectations ; extra == 'sql-profiles'
Requires-Dist: tabulate ; extra == 'sql-profiles'
Requires-Dist: avro-python3 (>=1.8.2) ; extra == 'sql-profiles'
Provides-Extra: sqlalchemy
Requires-Dist: entrypoints ; extra == 'sqlalchemy'
Requires-Dist: avro-gen3 (==0.6.0) ; extra == 'sqlalchemy'
Requires-Dist: sqlalchemy (==1.3.24) ; extra == 'sqlalchemy'
Requires-Dist: python-dateutil ; extra == 'sqlalchemy'
Requires-Dist: toml (>=0.10.0) ; extra == 'sqlalchemy'
Requires-Dist: PyYAML ; extra == 'sqlalchemy'
Requires-Dist: expandvars (>=0.6.5) ; extra == 'sqlalchemy'
Requires-Dist: stackprinter ; extra == 'sqlalchemy'
Requires-Dist: docker ; extra == 'sqlalchemy'
Requires-Dist: click (>=6.0.0) ; extra == 'sqlalchemy'
Requires-Dist: click-default-group ; extra == 'sqlalchemy'
Requires-Dist: tabulate ; extra == 'sqlalchemy'
Requires-Dist: avro-python3 (>=1.8.2) ; extra == 'sqlalchemy'
Provides-Extra: superset
Requires-Dist: entrypoints ; extra == 'superset'
Requires-Dist: avro-gen3 (==0.6.0) ; extra == 'superset'
Requires-Dist: requests ; extra == 'superset'
Requires-Dist: python-dateutil ; extra == 'superset'
Requires-Dist: toml (>=0.10.0) ; extra == 'superset'
Requires-Dist: PyYAML ; extra == 'superset'
Requires-Dist: expandvars (>=0.6.5) ; extra == 'superset'
Requires-Dist: stackprinter ; extra == 'superset'
Requires-Dist: docker ; extra == 'superset'
Requires-Dist: click (>=6.0.0) ; extra == 'superset'
Requires-Dist: click-default-group ; extra == 'superset'
Requires-Dist: tabulate ; extra == 'superset'
Requires-Dist: avro-python3 (>=1.8.2) ; extra == 'superset'
